TesterhomeWikiMacacaHejiFix1/README.md
TesterhomeWikiMacacaHejiFix1/__init__.py
TesterhomeWikiMacacaHejiFix1/__main__.py
TesterhomeWikiMacacaHejiFix1/file.epub
TesterhomeWikiMacacaHejiFix1/index.html
TesterhomeWikiMacacaHejiFix1/css/__init__.py
TesterhomeWikiMacacaHejiFix1/css/annotations.css
TesterhomeWikiMacacaHejiFix1/css/main.css
TesterhomeWikiMacacaHejiFix1/css/normalize.css
TesterhomeWikiMacacaHejiFix1/css/popup.css
TesterhomeWikiMacacaHejiFix1/font/__init__.py
TesterhomeWikiMacacaHejiFix1/font/fontello.eot
TesterhomeWikiMacacaHejiFix1/font/fontello.svg
TesterhomeWikiMacacaHejiFix1/font/fontello.ttf
TesterhomeWikiMacacaHejiFix1/font/fontello.woff
TesterhomeWikiMacacaHejiFix1/img/__init__.py
TesterhomeWikiMacacaHejiFix1/img/annotator-glyph-sprite.png
TesterhomeWikiMacacaHejiFix1/img/annotator-icon-sprite.png
TesterhomeWikiMacacaHejiFix1/img/apple-touch-icon.png
TesterhomeWikiMacacaHejiFix1/img/cancelfullscreen.png
TesterhomeWikiMacacaHejiFix1/img/close.png
TesterhomeWikiMacacaHejiFix1/img/fullscreen.png
TesterhomeWikiMacacaHejiFix1/img/loader.gif
TesterhomeWikiMacacaHejiFix1/img/menu-icon.png
TesterhomeWikiMacacaHejiFix1/img/save.png
TesterhomeWikiMacacaHejiFix1/img/saved.png
TesterhomeWikiMacacaHejiFix1/img/settings-s.png
TesterhomeWikiMacacaHejiFix1/img/settings.png
TesterhomeWikiMacacaHejiFix1/img/star.png
TesterhomeWikiMacacaHejiFix1/js/__init__.py
TesterhomeWikiMacacaHejiFix1/js/epub.js
TesterhomeWikiMacacaHejiFix1/js/epub.min.js
TesterhomeWikiMacacaHejiFix1/js/epub.min.map
TesterhomeWikiMacacaHejiFix1/js/hooks.min.js
TesterhomeWikiMacacaHejiFix1/js/hooks.min.map
TesterhomeWikiMacacaHejiFix1/js/reader.js
TesterhomeWikiMacacaHejiFix1/js/reader.js.map
TesterhomeWikiMacacaHejiFix1/js/reader.min.js
TesterhomeWikiMacacaHejiFix1/js/reader.min.map
TesterhomeWikiMacacaHejiFix1/js/hooks/__init__.py
TesterhomeWikiMacacaHejiFix1/js/hooks/extensions/__init__.py
TesterhomeWikiMacacaHejiFix1/js/hooks/extensions/highlight.js
testerhome_wiki_macaca_heji_fix1-2025.3.25.0.dist-info/METADATA
testerhome_wiki_macaca_heji_fix1-2025.3.25.0.dist-info/WHEEL
testerhome_wiki_macaca_heji_fix1-2025.3.25.0.dist-info/entry_points.txt
testerhome_wiki_macaca_heji_fix1-2025.3.25.0.dist-info/top_level.txt
testerhome_wiki_macaca_heji_fix1-2025.3.25.0.dist-info/RECORD
